katversion/__init__.py
katversion/build.py
katversion/version.py
katversion/test/test_version.py
katversion-1.2.data/scripts/kat-get-version.py
katversion-1.2.dist-info/LICENSE.txt
katversion-1.2.dist-info/METADATA
katversion-1.2.dist-info/WHEEL
katversion-1.2.dist-info/entry_points.txt
katversion-1.2.dist-info/pbr.json
katversion-1.2.dist-info/top_level.txt
katversion-1.2.dist-info/RECORD
