Metadata-Version: 2.1
Name: katversion
Version: 1.2
Summary: Reliable git-based versioning for Python packages
Home-page: https://github.com/ska-sa/katversion
Author: The MeerKAT CAM Team
Author-email: cam@ska.ac.za
License: BSD
Keywords: versioning meerkat ska
Platform: OS Independent
Classifier: Development Status :: 5 - Production/Stable
Classifier: Intended Audience :: Developers
Classifier: License :: OSI Approved :: BSD License
Classifier: Operating System :: OS Independent
Classifier: Programming Language :: Python
Classifier: Programming Language :: Python :: 2
Classifier: Programming Language :: Python :: 2.6
Classifier: Programming Language :: Python :: 2.7
Classifier: Programming Language :: Python :: 3
Classifier: Programming Language :: Python :: 3.3
Classifier: Programming Language :: Python :: 3.4
Classifier: Programming Language :: Python :: 3.5
Classifier: Programming Language :: Python :: 3.6
Classifier: Programming Language :: Python :: 3.7
Classifier: Programming Language :: Python :: 3.8
Classifier: Topic :: Software Development :: Version Control
Classifier: Topic :: System :: Software Distribution
Classifier: Topic :: Software Development :: Libraries :: Python Modules
Requires-Python: >=2.6, !=3.0.*, !=3.1.*, !=3.2.*, <4
License-File: LICENSE.txt
